Workbook

Sheet Home Loan
A1: 🏠 Bangladesh Home Loan | 🟡Yellow=input/formula দাও | 🟢Green=auto-calc
A3: 📌 INPUTS
A4: Loan Amount | B4: 3000000
A5: Annual Rate | B5: 0.09
A6: Tenure (Years) | B6: 15
A8: 📊 AUTO-CALC
A9: Monthly Rate (B5/12) | B9: =B5/12 -> 0.0075
A10: Total Months (B6×12) | B10: =B6*12 -> 180
A12: 🎯 RESULTS — Yellow cells-এ formula দাও
A13: Monthly EMI (PMT) | B13: =PMT(B5/12,B10,-B4) -> 30427.998 | D13: Hint: =PMT(B9,B10,-B4)
A14: Month 1 Interest (IPMT) | B14: =IPMT(B5/12,1,B10,-B4) -> 22500 | D14: Hint: =IPMT(B9,1,B10,-B4)
A15: Month 1 Principal (PPMT) | B15: =PPMT(B5/12,1,B10,-B4) -> 7927.9975 | D15: Hint: =PPMT(B9,1,B10,-B4)
A16: Verify: IPMT+PPMT=EMI? | B16: =B14+B15 -> 30427.998 | D16: Hint: =B14+B15
A17: Year 5 Interest (month 60) | B17: =IPMT(B5/12,60,B10,-B4) -> 18107.685 | D17: Hint: =IPMT(B9,60,B10,-B4)
A18: Max loan (৳৩০,০০০ EMI) | B18: =PV(B5/12,B10,-30000) -> 2957802.3 | D18: Hint: =PV(B9,B10,-30000)
A19: Months if ৳৩৫,০০০ EMI | B19: =NPER(B5/12,-35000,B4) -> 137.79676 | D19: Hint: =NPER(B9,-35000,B4)
A20: Total Payment | B20: =B13*B10 -> 5477039.6 | D20: Hint: =B13*B10
A21: Total Interest | B21: =B20-B4 -> 2477039.6 | D21: Hint: =B20-B4
A23: 🏦 Bank Comparison (৳৩০ লাখ, ১৫ বছর)
A24: Bank | B24: Rate | C24: EMI | D24: Total Payment | E24: Total Interest | F24: vs 9% Base | G24: Note
A25: DBBL | B25: 0.09 | C25: =PMT(B25/12,$B$10,-$B$4) -> 30427.998 | D25: =C25*$B$10 -> 5477039.6 | E25: =D25-$B$4 -> 2477039.6 | F25: =E25-$E$25 -> 0 | G25: Base
A26: BRAC Bank | B26: 0.095 | C26: =PMT(B26/12,$B$10,-$B$4) -> 31326.74 | D26: =C26*$B$10 -> 5638813.3 | E26: =D26-$B$4 -> 2638813.3 | F26: =E26-$E$25 -> 161773.73 | G26: Popular
A27: Islami Bank | B27: 0.1 | C27: =PMT(B27/12,$B$10,-$B$4) -> 32238.154 | D27: =C27*$B$10 -> 5802867.6 | E27: =D27-$B$4 -> 2802867.6 | F27: =E27-$E$25 -> 325828.08 | G27: Halal
A28: Sonali Bank | B28: 0.085 | C28: =PMT(B28/12,$B$10,-$B$4) -> 29542.187 | D28: =C28*$B$10 -> 5317593.6 | E28: =D28-$B$4 -> 2317593.6 | F28: =E28-$E$25 -> -159445.94 | G28: Govt

Sheet Amortization Table
A1: 📋 Amortization Table | Row 4-এ formula লেখো → Row 183 পর্যন্ত drag করো (১৮০ months)
A2: Note: 'Home Loan' sheet-এর inputs use করো। $ দিয়ে lock করো।
A3: Month | B3: Opening Balance | C3: EMI | D3: Interest (IPMT) | E3: Principal (PPMT) | F3: Closing Balance | H3: Expected Answers
A4: 1 | B4: 3000000 | C4: =PMT('Home Loan'!$B$9,'Home Loan'!$B$10,-'Home Loan'!$B$4) -> 30427.998 | D4: =IPMT('Home Loan'!$B$9,A4,'Home Loan'!$B$10,-'Home Loan'!$B$4) -> 22500 | E4: =C4-D4 -> 7927.9975 | F4: =B4-E4 -> 2992072 | H4: Month | I4: Opening | J4: EMI | K4: Interest | L4: Principal | M4: Closing
A5: =A4+1 -> 2 | B5: =F4 -> 2992072 | C5: =PMT('Home Loan'!$B$9,'Home Loan'!$B$10,-'Home Loan'!$B$4) -> 30427.998 | D5: =IPMT('Home Loan'!$B$9,A5,'Home Loan'!$B$10,-'Home Loan'!$B$4) -> 22440.54 | E5: =C5-D5 -> 7987.4575 | F5: =B5-E5 -> 2984084.5 | H5: 1 | I5: ৳৩০,০০,০০০ | J5: ৳৩০,৪২৮ | K5: ৳২২,৫০০ | L5: ৳৭,৯২৮ | M5: ৳২৯,৯২,০৭২
A6: =A5+1 -> 3 | B6: =F5 -> 2984084.5 | C6: =PMT('Home Loan'!$B$9,'Home Loan'!$B$10,-'Home Loan'!$B$4) -> 30427.998 | D6: =IPMT('Home Loan'!$B$9,A6,'Home Loan'!$B$10,-'Home Loan'!$B$4) -> 22380.634 | E6: =C6-D6 -> 8047.3634 | F6: =B6-E6 -> 2976037.2 | H6: 60 | I6: ৳২৫,৫২,৮৪৫ | J6: ৳৩০,৪২৮ | K6: ৳১৯,১৪৬ | L6: ৳১১,২৮২ | M6: ৳২৫,৪১,৫৬৩
A7: =A6+1 -> 4 | B7: =F6 -> 2976037.2 | C7: =PMT('Home Loan'!$B$9,'Home Loan'!$B$10,-'Home Loan'!$B$4) -> 30427.998 | D7: =IPMT('Home Loan'!$B$9,A7,'Home Loan'!$B$10,-'Home Loan'!$B$4) -> 22320.279 | E7: =C7-D7 -> 8107.7187 | F7: =B7-E7 -> 2967929.5 | H7: 120 | I7: ৳১৭,৬৩,৯৪৫ | J7: ৳৩০,৪২৮ | K7: ৳১৩,২৩০ | L7: ৳১৭,১৯৮ | M7: ৳১৭,৪৬,৭৪৭
A8: =A7+1 -> 5 | B8: =F7 -> 2967929.5 | C8: =PMT('Home Loan'!$B$9,'Home Loan'!$B$10,-'Home Loan'!$B$4) -> 30427.998 | D8: =IPMT('Home Loan'!$B$9,A8,'Home Loan'!$B$10,-'Home Loan'!$B$4) -> 22259.471 | E8: =C8-D8 -> 8168.5266 | F8: =B8-E8 -> 2959760.9 | H8: 180 | I8: ৳৩০,২০৫ | J8: ৳৩০,৪২৮ | K8: ৳২২৭ | L8: ৳৩০,২০১ | M8: ≈ ৳০
A9: =A8+1 -> 6 | B9: =F8 -> 2959760.9 | C9: =PMT('Home Loan'!$B$9,'Home Loan'!$B$10,-'Home Loan'!$B$4) -> 30427.998 | D9: =IPMT('Home Loan'!$B$9,A9,'Home Loan'!$B$10,-'Home Loan'!$B$4) -> 22198.207 | E9: =C9-D9 -> 8229.7905 | F9: =B9-E9 -> 2951531.1
A10: =A9+1 -> 7 | B10: =F9 -> 2951531.1 | C10: =PMT('Home Loan'!$B$9,'Home Loan'!$B$10,-'Home Loan'!$B$4) -> 30427.998 | D10: =IPMT('Home Loan'!$B$9,A10,'Home Loan'!$B$10,-'Home Loan'!$B$4) -> 22136.484 | E10: =C10-D10 -> 8291.5139 | F10: =B10-E10 -> 2943239.6
A11: =A10+1 -> 8 | B11: =F10 -> 2943239.6 | C11: =PMT('Home Loan'!$B$9,'Home Loan'!$B$10,-'Home Loan'!$B$4) -> 30427.998 | D11: =IPMT('Home Loan'!$B$9,A11,'Home Loan'!$B$10,-'Home Loan'!$B$4) -> 22074.297 | E11: =C11-D11 -> 8353.7003 | F11: =B11-E11 -> 2934885.9
A12: =A11+1 -> 9 | B12: =F11 -> 2934885.9 | C12: =PMT('Home Loan'!$B$9,'Home Loan'!$B$10,-'Home Loan'!$B$4) -> 30427.998 | D12: =IPMT('Home Loan'!$B$9,A12,'Home Loan'!$B$10,-'Home Loan'!$B$4) -> 22011.644 | E12: =C12-D12 -> 8416.353 | F12: =B12-E12 -> 2926469.6
A13: =A12+1 -> 10 | B13: =F12 -> 2926469.6 | C13: =PMT('Home Loan'!$B$9,'Home Loan'!$B$10,-'Home Loan'!$B$4) -> 30427.998 | D13: =IPMT('Home Loan'!$B$9,A13,'Home Loan'!$B$10,-'Home Loan'!$B$4) -> 21948.522 | E13: =C13-D13 -> 8479.4757 | F13: =B13-E13 -> 2917990.1
A14: =A13+1 -> 11 | B14: =F13 -> 2917990.1 | C14: =PMT('Home Loan'!$B$9,'Home Loan'!$B$10,-'Home Loan'!$B$4) -> 30427.998 | D14: =IPMT('Home Loan'!$B$9,A14,'Home Loan'!$B$10,-'Home Loan'!$B$4) -> 21884.926 | E14: =C14-D14 -> 8543.0718 | F14: =B14-E14 -> 2909447
A15: =A14+1 -> 12 | B15: =F14 -> 2909447 | C15: =PMT('Home Loan'!$B$9,'Home Loan'!$B$10,-'Home Loan'!$B$4) -> 30427.998 | D15: =IPMT('Home Loan'!$B$9,A15,'Home Loan'!$B$10,-'Home Loan'!$B$4) -> 21820.853 | E15: =C15-D15 -> 8607.1448 | F15: =B15-E15 -> 2900839.9
A16: =A15+1 -> 13 | B16: =F15 -> 2900839.9 | C16: =PMT('Home Loan'!$B$9,'Home Loan'!$B$10,-'Home Loan'!$B$4) -> 30427.998 | D16: =IPMT('Home Loan'!$B$9,A16,'Home Loan'!$B$10,-'Home Loan'!$B$4) -> 21756.299 | E16: =C16-D16 -> 8671.6984 | F16: =B16-E16 -> 2892168.2
A17: =A16+1 -> 14 | B17: =F16 -> 2892168.2 | C17: =PMT('Home Loan'!$B$9,'Home Loan'!$B$10,-'Home Loan'!$B$4) -> 30427.998 | D17: =IPMT('Home Loan'!$B$9,A17,'Home Loan'!$B$10,-'Home Loan'!$B$4) -> 21691.261 | E17: =C17-D17 -> 8736.7361 | F17: =B17-E17 -> 2883431.5
A18: =A17+1 -> 15 | B18: =F17 -> 2883431.5 | C18: =PMT('Home Loan'!$B$9,'Home Loan'!$B$10,-'Home Loan'!$B$4) -> 30427.998 | D18: =IPMT('Home Loan'!$B$9,A18,'Home Loan'!$B$10,-'Home Loan'!$B$4) -> 21625.736 | E18: =C18-D18 -> 8802.2616 | F18: =B18-E18 -> 2874629.2
A19: =A18+1 -> 16 | B19: =F18 -> 2874629.2 | C19: =PMT('Home Loan'!$B$9,'Home Loan'!$B$10,-'Home Loan'!$B$4) -> 30427.998 | D19: =IPMT('Home Loan'!$B$9,A19,'Home Loan'!$B$10,-'Home Loan'!$B$4) -> 21559.719 | E19: =C19-D19 -> 8868.2786 | F19: =B19-E19 -> 2865760.9
A20: =A19+1 -> 17 | B20: =F19 -> 2865760.9 | C20: =PMT('Home Loan'!$B$9,'Home Loan'!$B$10,-'Home Loan'!$B$4) -> 30427.998 | D20: =IPMT('Home Loan'!$B$9,A20,'Home Loan'!$B$10,-'Home Loan'!$B$4) -> 21493.207 | E20: =C20-D20 -> 8934.7907 | F20: =B20-E20 -> 2856826.1
... A183: =A182+1 -> 180 | B183: =F182 -> 30201.486 | C183: =PMT('Home Loan'!$B$9,'Home Loan'!$B$10,-'Home Loan'!$B$4) -> 30427.998 | D183: =IPMT('Home Loan'!$B$9,A183,'Home Loan'!$B$10,-'Home Loan'!$B$4) -> 226.51115 | E183: =C183-D183 -> 30201.486 | F183: =B183-E183 -> -4.4383341e-10

Sheet Rate Sensitivity
A1: 📊 Rate Sensitivity | 🟡 B column-এ PMT formula দাও | ৳৩০ লাখ, ১৫ বছর
A3: Annual Rate | B3: Monthly EMI | C3: vs 9% Base | D3: Total 15yr | E3: Total Interest | F3: Verdict
A4: 0.07 | B4: =PMT(A4/12,180,-3000000) -> 26964.848 | C4: =B4-$B$6 -> -3463.1494 | D4: =B4*180 -> 4853672.7 | E4: =D4-3000000 -> 1853672.7 | F4: 💚 সবচেয়ে সস্তা
A5: 0.08 | B5: =PMT(A5/12,180,-3000000) -> 28669.563 | C5: =B5-$B$6 -> -1758.435 | D5: =B5*180 -> 5160521.3 | E5: =D5-3000000 -> 2160521.3 | F5: 💚 ভালো
A6: 0.09 | B6: =PMT(A6/12,180,-3000000) -> 30427.998 | C6: =B6-$B$6 -> 0 | D6: =B6*180 -> 5477039.6 | E6: =D6-3000000 -> 2477039.6 | F6: 🟡 Base
A7: 0.1 | B7: =PMT(A7/12,180,-3000000) -> 32238.154 | C7: =B7-$B$6 -> 1810.156 | D7: =B7*180 -> 5802867.6 | E7: =D7-3000000 -> 2802867.6 | F7: 🔴 বেশি
A8: 0.11 | B8: =PMT(A8/12,180,-3000000) -> 34097.908 | C8: =B8-$B$6 -> 3669.9105 | D8: =B8*180 -> 6137623.4 | E8: =D8-3000000 -> 3137623.4 | F8: 🔴 অনেক বেশি
A12: 🔧 Bonus: What-If Data Table
A13: Data → What-If Analysis → Data Table। Row input: A4 (rate). Column: Loan amount. একটা table-এ সব combination!
A15: =PMT(G16/12,180,-G15) -> 17976.565 | B15: 2000000 | C15: 2500000 | D15: 3000000 | E15: 3500000 | G15: 2000000
A16: =7% -> 0.07 | B16: 17976.565 | C16: 22470.707 | D16: 26964.848 | E16: 31458.989 | G16: 0.07
A17: 0.08 | B17: 19113.042 | C17: 23891.302 | D17: 28669.563 | E17: 33447.823
A18: 0.09 | B18: 20285.332 | C18: 25356.665 | D18: 30427.998 | E18: 35499.33
A19: 0.1 | B19: 21492.102 | C19: 26865.128 | D19: 32238.154 | E19: 37611.179
